{
  "id": "ps-scoop-119l-main-2026-03-25",
  "source": "PokerStars",
  "tournament": "SCOOP 119-L: $109 NLHE [Main Event, $1.5M Gtd, 4-Day Event]",
  "gameType": "NLH",
  "format": "regular",
  "currency": "USD",
  "buyIn": 109,
  "entries": 16883,
  "uniqueEntries": 10314,
  "reEntries": 6569,
  "prizePool": 1688300,
  "paid": 2415,
  "capturedAt": "2026-03-25",
  "partial": false,
  "places": [
    { "from": 1,    "to": 1,    "prize": 181540.89 },
    { "from": 2,    "to": 2,    "prize": 129401.94 },
    { "from": 3,    "to": 3,    "prize": 92242.12 },
    { "from": 4,    "to": 4,    "prize": 65753.37 },
    { "from": 5,    "to": 5,    "prize": 46871.25 },
    { "from": 6,    "to": 6,    "prize": 33411.45 },
    { "from": 7,    "to": 7,    "prize": 23816.84 },
    { "from": 8,    "to": 8,    "prize": 16977.54 },
    { "from": 9,    "to": 9,    "prize": 12102.24 },
    { "from": 10,   "to": 11,   "prize": 8626.87 },
    { "from": 12,   "to": 13,   "prize": 6149.63 },
    { "from": 14,   "to": 17,   "prize": 4383.67 },
    { "from": 18,   "to": 23,   "prize": 3142.26 },
    { "from": 24,   "to": 31,   "prize": 2637.79 },
    { "from": 32,   "to": 47,   "prize": 2214.37 },
    { "from": 48,   "to": 71,   "prize": 1858.81 },
    { "from": 72,   "to": 103,  "prize": 1560.32 },
    { "from": 104,  "to": 143,  "prize": 1309.61 },
    { "from": 144,  "to": 191,  "prize": 1099.42 },
    { "from": 192,  "to": 247,  "prize": 922.82 },
    { "from": 248,  "to": 311,  "prize": 774.76 },
    { "from": 312,  "to": 383,  "prize": 650.33 },
    { "from": 384,  "to": 527,  "prize": 545.82 },
    { "from": 528,  "to": 719,  "prize": 458.20 },
    { "from": 720,  "to": 959,  "prize": 384.59 },
    { "from": 960,  "to": 1247, "prize": 322.97 },
    { "from": 1248, "to": 1583, "prize": 271.14 },
    { "from": 1584, "to": 1967, "prize": 227.58 },
    { "from": 1968, "to": 2415, "prize": 190.94 }
  ]
}
